<?xml version='1.0' encoding='UTF-8'?>
<?xml-stylesheet type="text/xsl" href="frame.xsl"?>
<frame xmlns="http://framenet.icsi.berkeley.edu" xmlns:xsi="http://www.w3.org/2001/XMLSchema-instance" cBy="MJE" cDate="01/19/2005 01:09:32 PST Wed" name="Taking_sides" ID="1306" xsi:schemaLocation="../schema/frame.xsd">
  <definition>&lt;def-root&gt;A &lt;fen&gt;Cognizer&lt;/fen&gt; has a relatively fixed positive or negative point of view towards an &lt;fen&gt;Issue&lt;/fen&gt;.  A &lt;fen&gt;Side&lt;/fen&gt; in a debate concerning an &lt;fen&gt;Issue&lt;/fen&gt; or an &lt;fen&gt;Action&lt;/fen&gt; of a &lt;fen&gt;Side&lt;/fen&gt; may stand in for the &lt;fen&gt;Issue&lt;/fen&gt;.  The &lt;fen&gt;Cognizer&lt;/fen&gt;'s &lt;fen&gt;Degree&lt;/fen&gt; of alignment may also be specified.

&lt;ex&gt;In interviews , it seems like &lt;fex name="cog"&gt;everyone&lt;/fex&gt; &lt;m&gt;is&lt;/m&gt; &lt;fex name="deg"&gt;completely&lt;/fex&gt; &lt;t&gt;against&lt;/t&gt; &lt;fex name="iss"&gt;this expenditure&lt;/fex&gt; .&lt;/ex&gt;
&lt;/def-root&gt;</definition>
  <FE bgColor="FF0000" fgColor="FFFFFF" coreType="Core" cBy="MJE" cDate="01/19/2005 01:32:20 PST Wed" abbrev="cog" name="Cognizer" ID="7433">
    <definition>&lt;def-root&gt;The individual that holds an opinion on an &lt;fen&gt;Issue&lt;/fen&gt; or Side.&lt;/def-root&gt;</definition>
    <semType name="Sentient" ID="5"/>
  </FE>
  <FE bgColor="008000" fgColor="FFFFFF" coreType="Core" cBy="MJE" cDate="01/19/2005 01:33:21 PST Wed" abbrev="iss" name="Issue" ID="7434">
    <definition>&lt;def-root&gt;The matter, usually concerning a course of action, which the &lt;fen&gt;Cognizer&lt;/fen&gt; has a positive or negative opinion about.&lt;/def-root&gt;</definition>
  </FE>
  <FE bgColor="0000FF" fgColor="FFFFFF" coreType="Core" cBy="MJE" cDate="01/19/2005 01:35:33 PST Wed" abbrev="sid" name="Side" ID="7435">
    <definition>&lt;def-root&gt;The party or individual (generally associated with a particular position on an &lt;fen&gt;Issue&lt;/fen&gt;) that the &lt;fen&gt;Cognizer&lt;/fen&gt; has an opinion about.&lt;/def-root&gt;</definition>
  </FE>
  <FE bgColor="FF69B4" fgColor="FFFFFF" coreType="Peripheral" cBy="MJE" cDate="01/19/2005 01:48:13 PST Wed" abbrev="deg" name="Degree" ID="7436">
    <definition>&lt;def-root&gt;The &lt;fen&gt;Degree&lt;/fen&gt; to which the &lt;fen&gt;Cognizer&lt;/fen&gt; supports or opposes something.&lt;/def-root&gt;</definition>
    <semType name="Degree" ID="172"/>
  </FE>
  <FE bgColor="800080" fgColor="FFFFFF" coreType="Peripheral" cBy="JKR" cDate="06/15/2005 10:34:10 PDT Wed" abbrev="tim" name="Time" ID="8160">
    <definition>&lt;def-root&gt;The time period during which the &lt;fen&gt;Cognizer&lt;/fen&gt; has the indicated point of view towards the &lt;fen&gt;Issue&lt;/fen&gt;.

&lt;ex&gt;&lt;fex name="Time"&gt;Last year&lt;/fex&gt; she &lt;t&gt;opposed&lt;/t&gt; the bill, but changed her mind after she received correspondence supporting the bill. &lt;/ex&gt;&lt;/def-root&gt;</definition>
    <semType name="Time" ID="141"/>
  </FE>
  <FE bgColor="FFA500" fgColor="FFFFFF" coreType="Extra-Thematic" cBy="JKR" cDate="06/15/2005 10:38:44 PDT Wed" abbrev="exp" name="Explanation" ID="8161">
    <definition>&lt;def-root&gt;The &lt;fen&gt;Explanation&lt;/fen&gt; is a proposition denoting a state of affairs from which the &lt;fen&gt;Cognizer&lt;/fen&gt;'s taking the indicated view on the &lt;fen&gt;Issue&lt;/fen&gt; logically follows.

&lt;ex&gt;Could it be that he &lt;t&gt;sided&lt;/t&gt; with them &lt;fex name="exp"&gt;because it was the constitutionaly correct thing to do&lt;/fex&gt;?&lt;/ex&gt;&lt;/def-root&gt;</definition>
    <semType name="State_of_affairs" ID="177"/>
  </FE>
  <FE bgColor="00008B" fgColor="FFFFFF" coreType="Core" cBy="JKR" cDate="10/27/2005 05:03:53 PDT Thu" abbrev="pos" name="Action" ID="9155">
    <definition>&lt;def-root&gt;An action taken by a &lt;fen&gt;Side&lt;/fen&gt; or a view that the &lt;fen&gt;Side&lt;/fen&gt; takes on an issue which the &lt;fen&gt;Cognizer&lt;/fen&gt; either supports or opposes.

&lt;/def-root&gt;</definition>
  </FE>
  <FE bgColor="7CCD73" fgColor="FFFFFF" coreType="Extra-Thematic" cBy="KmG" cDate="08/03/2006 02:41:32 PDT Thu" abbrev="Des" name="Descriptor" ID="10443">
    <definition>&lt;def-root&gt;This FE describes the person or element that is taking a side. &lt;/def-root&gt;</definition>
  </FE>
  <FE bgColor="9F79EE" fgColor="FFFFFF" coreType="Extra-Thematic" cBy="KmG" cDate="08/08/2006 02:44:06 PDT Tue" abbrev="Par" name="Particular_iteration" ID="10452">
    <definition>&lt;def-root&gt;Expressions marked with this extra-thematic FE modify a non-iterative use of the target, and indicate that it is conceived as embedded within an iterated series of similar events or states. In addition, most expressions of Particular_iteration indicate which instance of the series is being referred to.&lt;/def-root&gt;</definition>
  </FE>
  <FE bgColor="00BFFF" fgColor="FFFFFF" coreType="Peripheral" cBy="KmG" cDate="08/08/2006 02:57:36 PDT Tue" abbrev="Man" name="Manner" ID="10453">
    <definition>&lt;def-root&gt;Any description of the Taking_sides which is not covered by more specific FEs, including epistemic modification secondary effects (quietly, loudly), and general descriptions comparing events (the same way). It may also indicate salient characteristics of the &lt;fen&gt;Cognizer&lt;/fen&gt; that affect the action (reluctantly, meekly).&lt;/def-root&gt;</definition>
  </FE>
  <FE bgColor="FFFF00" fgColor="000000" coreType="Extra-Thematic" cBy="KmG" cDate="01/03/2007 01:09:36 PST Wed" abbrev="Con" name="Concessive" ID="10941">
    <definition>&lt;def-root&gt;This FE signifies that the state of affairs expressed by the main clause (containing the target) occurs or holds, and something other than that state of affairs would be expected given the state of affairs in the concessive clause. &lt;/def-root&gt;</definition>
  </FE>
  <FE bgColor="EEE8AA" fgColor="9400D3" coreType="Peripheral" cBy="KmG" cDate="06/12/2007 02:11:19 PDT Tue" abbrev="pla" name="Place" ID="11886">
    <definition>&lt;def-root&gt;The location where the &lt;fen&gt;Cognizer&lt;/fen&gt; takes &lt;fen&gt;Side&lt;/fen&gt;s on an &lt;fen&gt;Issue&lt;/fen&gt; .&lt;/def-root&gt;</definition>
  </FE>
  <FEcoreSet>
    <memberFE name="Side" ID="7435"/>
    <memberFE name="Issue" ID="7434"/>
    <memberFE name="Action" ID="9155"/>
  </FEcoreSet>
  <frameRelation type="Inherits from"/>
  <frameRelation type="Is Inherited by"/>
  <frameRelation type="Perspective on"/>
  <frameRelation type="Is Perspectivized in"/>
  <frameRelation type="Uses">
    <relatedFrame ID="1412">Opinion</relatedFrame>
    <relatedFrame ID="1383">Desirable_event</relatedFrame>
  </frameRelation>
  <frameRelation type="Is Used by">
    <relatedFrame ID="1497">Giving_in</relatedFrame>
    <relatedFrame ID="349">Partiality</relatedFrame>
    <relatedFrame ID="2587">Protest</relatedFrame>
    <relatedFrame ID="93">Hostile_encounter</relatedFrame>
  </frameRelation>
  <frameRelation type="Subframe of"/>
  <frameRelation type="Has Subframe(s)"/>
  <frameRelation type="Precedes"/>
  <frameRelation type="Is Preceded by"/>
  <frameRelation type="Is Inchoative of"/>
  <frameRelation type="Is Causative of"/>
  <frameRelation type="See also"/>
</frame>
