<?xml version='1.0' encoding='UTF-8'?>
<lexUnit xmlns="http://framenet.icsi.berkeley.edu" xmlns:xsi="http://www.w3.org/2001/XMLSchema-instance" xmlns:skos="http://www.w3.org/2004/02/skos/core#" status="Created" POS="A" name="slank.a" ID="1612186638808" frame="Body_description_holistic" frameID="157" totalAnnotated="0" xsi:schemaLocation="../schema/lexUnit.xsd" skos:closeMatch="http://rdf.cltl.nl/rbn/lexicon-1.0-lu-r_a-14911" lu_type="singleton">
  <header>
    <frame>
      <FE fgColor="FFFFFF" bgColor="FF69B4" type="Peripheral" abbrev="Degr" name="Degree"/>
      <FE fgColor="FFFFFF" bgColor="1E90FF" type="Core" abbrev="Fig" name="Figure"/>
      <FE fgColor="FFFFFF" bgColor="FF0000" type="Core" abbrev="Ind" name="Individual"/>
    </frame>
  </header>
  <definition>rank</definition>
  <lexeme POS="A" breakBefore="false" headword="false" name="slank" order="1"/>
</lexUnit>
